libasciitounicode/__init__.py
libasciitounicode/converter.py
libasciitounicode-0.1.dist-info/METADATA
libasciitounicode-0.1.dist-info/RECORD
libasciitounicode-0.1.dist-info/WHEEL
libasciitounicode-0.1.dist-info/top_level.txt
