Metadata-Version: 2.1
Name: libasciitounicode
Version: 0.1
Summary: Library to convert ASCII encodings to unicode
Home-page: https://github.com/akuru/libasciitounicode
Author: Keshan Sodimana
Author-email: keshan88@gmail.com
License: MIT
Platform: UNKNOWN
Requires-Dist: PyYAML
